exec_client.py
exec_server.py
blocks/__init__.py
blocks/common_details.py
blocks/mine/__init__.py
blocks/mine/actions_rdefs_basic.txt
blocks/mine/classCandidates.py
blocks/mine/classCharbon.py
blocks/mine/classCharbonGMiss.py
blocks/mine/classCharbonGStd.py
blocks/mine/classCharbonGreedy.py
blocks/mine/classCharbonTAlt.py
blocks/mine/classCharbonTLayer.py
blocks/mine/classCharbonXFIM.py
blocks/mine/classCol.py
blocks/mine/classConstraints.py
blocks/mine/classContent.py
blocks/mine/classDTreeTools.py
blocks/mine/classData.py
blocks/mine/classDataExtension.py
blocks/mine/classMiner.py
blocks/mine/classPackage.py
blocks/mine/classPreferencesManager.py
blocks/mine/classProps.py
blocks/mine/classQuery.py
blocks/mine/classRedescription.py
blocks/mine/classRndFactory.py
blocks/mine/classSParts.py
blocks/mine/classSouvenirs.py
blocks/mine/csv_reader.py
blocks/mine/dataext_confdef.xml
blocks/mine/exec_clired.py
blocks/mine/fields_rdefs_basic.txt
blocks/mine/fields_rdefs_more.txt
blocks/mine/fields_vdefs_basic.txt
blocks/mine/fields_vdefs_more.txt
blocks/mine/folds_confdef.xml
blocks/mine/inout_confdef.xml
blocks/mine/miner_confdef.xml
blocks/mine/mkPartsTypes.py
blocks/mine/prepare_polygons.py
blocks/mine/redquery_parser.py
blocks/mine/rnd_confdef.xml
blocks/mine/toolICDict.py
blocks/mine/toolICList.py
blocks/mine/toolLog.py
blocks/mine/toolXML.py
blocks/mine/grako/__init__.py
blocks/mine/grako/__main__.py
blocks/mine/grako/ast.py
blocks/mine/grako/bootstrap.py
blocks/mine/grako/buffering.py
blocks/mine/grako/codegen.py
blocks/mine/grako/contexts.py
blocks/mine/grako/diagrams.py
blocks/mine/grako/exceptions.py
blocks/mine/grako/grammars.py
blocks/mine/grako/model.py
blocks/mine/grako/parsing.py
blocks/mine/grako/rendering.py
blocks/mine/grako/semantics.py
blocks/mine/grako/tool.py
blocks/mine/grako/util.py
blocks/work/__init__.py
blocks/work/classWorkClient.py
blocks/work/classWorkInactive.py
blocks/work/classWorkLocal.py
blocks/work/classWorkServer.py
python_clired-6.0.8.dist-info/LICENSE
python_clired-6.0.8.dist-info/METADATA
python_clired-6.0.8.dist-info/WHEEL
python_clired-6.0.8.dist-info/entry_points.txt
python_clired-6.0.8.dist-info/top_level.txt
python_clired-6.0.8.dist-info/RECORD
